ipyplots/__init__.py
ipyplots/d3.v3.min.js
ipyplots/graph.html
ipyplots/graphs.py
ipyplots/maps.py
ipyplots/plots.py
ipyviz-1.0.dist-info/DESCRIPTION.rst
ipyviz-1.0.dist-info/METADATA
ipyviz-1.0.dist-info/RECORD
ipyviz-1.0.dist-info/WHEEL
ipyviz-1.0.dist-info/metadata.json
ipyviz-1.0.dist-info/top_level.txt
