Metadata-Version: 2.0
Name: ipyviz
Version: 1.0
Summary: Visualisation package for IPython Notebooks
Home-page: UNKNOWN
Author: Martin Zellner
Author-email: martin.zellner@gmail.com
License: UNKNOWN
Platform: UNKNOWN
Requires: numpy
Requires: seaborn
Requires: matplotlib
Requires: networkx
Requires: IPython
Requires: folium
